[{"id":666,"modifiedDate":"2020-04-30T03:18:24","fileModifiedDate":"2021-07-17T13:43:09.6224202-07:00","fileCreatedDate":"1600-12-31T16:00:00-08:00","filePath":"D:/GameDev_Unity/Unity Projects 2021/3D Survival Shooter Pro/3D Survival Shooter Pro/Assets/GameDevHQ/FileBase/3D/Props/Weapons/Baretta"},{"id":6298,"modifiedDate":"2020-10-05T21:14:19","fileModifiedDate":"2021-07-17T13:44:36.0725783-07:00","fileCreatedDate":"2021-07-17T13:44:34.9436398-07:00","filePath":"D:/GameDev_Unity/Unity Projects 2021/3D Survival Shooter Pro/3D Survival Shooter Pro/Assets/GameDevHQ/FileBase/3D/Characters/Monsters/Monster_06"}]